setup.py
django_huluku.egg-info/PKG-INFO
django_huluku.egg-info/SOURCES.txt
django_huluku.egg-info/dependency_links.txt
django_huluku.egg-info/not-zip-safe
django_huluku.egg-info/requires.txt
django_huluku.egg-info/top_level.txt
huluku/__init__.py
huluku/models.py