Metadata-Version: 1.0
Name: django-huluku
Version: 0.2
Summary: For making writing of policies easier
Home-page: http://github.com/lefootballroi/django-huluku
Author: Anthony Eli Agbenu
Author-email: eli.anthony.agbenu@gmail.com
License: MIT
Platform: UNKNOWN
